README.md
setup.py
weatherutil/__init__.py
weatherutil/util.py
weatherutilv1.egg-info/PKG-INFO
weatherutilv1.egg-info/SOURCES.txt
weatherutilv1.egg-info/dependency_links.txt
weatherutilv1.egg-info/top_level.txt