Metadata-Version: 2.4
Name: weatherutilv1
Version: 0.1.0
Summary: A sample package containing basic data stat methods
Author: Jarek Smith
Author-email: jarek.smith.88@gmail.com
Requires-Python: >=3.12.4, <4
Dynamic: author
Dynamic: author-email
Dynamic: description
Dynamic: requires-python
Dynamic: summary
